tar_paint/__init__.py
tar_paint/main.py
tar_paint-0.1.0.dist-info/LICENSE
tar_paint-0.1.0.dist-info/METADATA
tar_paint-0.1.0.dist-info/WHEEL
tar_paint-0.1.0.dist-info/entry_points.txt
tar_paint-0.1.0.dist-info/top_level.txt
tar_paint-0.1.0.dist-info/RECORD
