Metadata-Version: 2.1
Name: tar-paint
Version: 0.1.0
Summary: tar paint application
Home-page: https://github.com/natthphong/tar_pain
Author: Your Name
Author-email: jaroenpronprasit@gmail.com
Classifier: Programming Language :: Python :: 3
Classifier: License :: OSI Approved :: MIT License
Classifier: Operating System :: OS Independent
License-File: LICENSE
Requires-Dist: tkinter
